nvidia_eval_commons/__init__.py
nvidia_eval_commons/api_dataclasses.py
nvidia_eval_commons-25.5.2.dist-info/licenses/LICENSE
nvidia_eval_commons-25.5.2.dist-info/METADATA
nvidia_eval_commons-25.5.2.dist-info/WHEEL
nvidia_eval_commons-25.5.2.dist-info/top_level.txt
nvidia_eval_commons-25.5.2.dist-info/RECORD
