Metadata-Version: 2.4
Name: nvidia-eval-commons
Version: 25.5.2
License:                                  Apache License
Classifier: Development Status :: 5 - Production/Stable
Classifier: Programming Language :: Python :: 3
Classifier: License :: OSI Approved :: Apache Software License
Classifier: Operating System :: OS Independent
Requires-Python: >=3.9
License-File: LICENSE
Requires-Dist: jinja2
Requires-Dist: pydantic
Dynamic: license-file
